cctorch/__init__.py
cctorch/data.py
cctorch/model.py
cctorch/postprocess.py
cctorch/transforms.py
cctorch/util.py
CCTorch-0.1.2.dist-info/METADATA
CCTorch-0.1.2.dist-info/WHEEL
CCTorch-0.1.2.dist-info/top_level.txt
CCTorch-0.1.2.dist-info/RECORD
